setup.py
fertex/__init__.py
fertex/vorono.py
fertex.egg-info/PKG-INFO
fertex.egg-info/SOURCES.txt
fertex.egg-info/dependency_links.txt
fertex.egg-info/top_level.txt