Metadata-Version: 2.1
Name: fertex
Version: 0.0.1
Summary: Test 2023-04-27
